{
  "version": "7.2.2",
  "url": "https://bcai.site/updates/BingchaAI-7.2.2.exe",
  "sha256": "E456AE47DCD6A94C41B32F3D5C91C9683A96906153EEC2490AD3872DB1A83F0E",
  "size": 18271232,
  "changelog": "feat: fair-share quota",
  "minVersion": "4.0.0",
  "macOS": {
    "arm64": {
      "url": "https://bcai.site/updates/BingchaAI-7.2.2-arm64.dmg",
      "sha256": "2D0088897EA811639D7B6A5A423C2DDA10E9133B3950F55FDC1B86C1CBC5CC11",
      "size": 9204792
    },
    "amd64": {
      "url": "https://bcai.site/updates/BingchaAI-7.2.2-amd64.dmg",
      "sha256": "86DCF71758C2E7EAE9B8DF87C8B354B840A700388FD0165EEBE497BA540C4D16",
      "size": 9822692
    }
  },
  "linux": {
    "amd64": {
      "url": "https://bcai.site/updates/BingchaAI-7.2.2-linux-amd64.tar.gz",
      "sha256": "FE05D9F9EE68499A69291227DE9EB3B2B9E231E35919EE522E06CBADA52AF3F4",
      "size": 7691155
    }
  }
}
